mkdocs_pipeline_visualizer-0.4.2.dist-info/licenses/LICENSE
src/__init__.py
src/test_visualizer.py
src/visualizer.py
mkdocs_pipeline_visualizer-0.4.2.dist-info/METADATA
mkdocs_pipeline_visualizer-0.4.2.dist-info/WHEEL
mkdocs_pipeline_visualizer-0.4.2.dist-info/entry_points.txt
mkdocs_pipeline_visualizer-0.4.2.dist-info/top_level.txt
mkdocs_pipeline_visualizer-0.4.2.dist-info/RECORD
