Metadata-Version: 2.4
Name: mkdocs-pipeline-visualizer
Version: 0.4.2
Summary: generate MD documentation from tekton pipelines and tasks
Home-page: https://github.com/obegron/mkdocs-pipeline-visualizer
Author: Christer Grönblad
License-File: LICENSE
Requires-Dist: mkdocs
Dynamic: author
Dynamic: description
Dynamic: description-content-type
Dynamic: home-page
Dynamic: license-file
Dynamic: requires-dist
Dynamic: summary
